ntnx_api/__init__.py
ntnx_api/_version.py
ntnx_api/client.py
ntnx_api/prism.py
ntnx_api/test/__init__.py
ntnx_api/test/test_client.py
ntnx_api-1.5.0.dist-info/LICENSE.txt
ntnx_api-1.5.0.dist-info/METADATA
ntnx_api-1.5.0.dist-info/WHEEL
ntnx_api-1.5.0.dist-info/top_level.txt
ntnx_api-1.5.0.dist-info/RECORD
