Metadata-Version: 2.1
Name: ntnx-api
Version: 1.5.0
Summary: Nutanix API Library
Home-page: https://gitlab.com/nutanix-se/python/nutanix-api
Author: Ross Davies
Author-email: davies.ross@gmail.com
License: BSD 2-Clause
Keywords: ntnx,nutanix,hci,hyper-converged,rest,client,prism,prism-element,prism-central
Platform: UNKNOWN
Classifier: Operating System :: OS Independent
Classifier: Programming Language :: Python :: 3
Classifier: Programming Language :: Python :: 3.6
Classifier: Programming Language :: Python :: 3.7
Classifier: Programming Language :: Python :: 3.8
Classifier: Intended Audience :: Developers
Classifier: Intended Audience :: System Administrators
Classifier: License :: OSI Approved :: MIT License
Requires-Python: >=3.6
License-File: LICENSE.txt
Requires-Dist: urllib3 (==1.26.4)
Requires-Dist: requests (==2.25.1)
Requires-Dist: paramiko (==2.7.2)
Requires-Dist: deprecated (==1.2.12)
Requires-Dist: bitmath (==1.3.3.1)
Provides-Extra: pytest
Requires-Dist: tox ; extra == 'pytest'
Requires-Dist: pytest ; extra == 'pytest'
Provides-Extra: testing
Requires-Dist: tox ; extra == 'testing'
